smartyparse/__init__.py
smartyparse/core.py
smartyparse/parsers.py
smartyparse-0.1.3.dist-info/DESCRIPTION.rst
smartyparse-0.1.3.dist-info/METADATA
smartyparse-0.1.3.dist-info/RECORD
smartyparse-0.1.3.dist-info/WHEEL
smartyparse-0.1.3.dist-info/metadata.json
smartyparse-0.1.3.dist-info/top_level.txt
